pricedl/__init__.py
pricedl/config.py
pricedl/direct_dl.py
pricedl/main.py
pricedl/model.py
pricedl/price_flat_file.py
pricedl/quote.py
pricedl/beanprice/__init__.py
pricedl/beanprice/vanguard_au_detail.py
pricedl/beanprice/yahoo.py
pricedl/quotes/__init__.py
pricedl/quotes/ecb.py
pricedl/quotes/fixerio.py
pricedl/quotes/vanguard_au.py
pricedl/quotes/vanguard_au_2023_detail.py
pricedl/quotes/yahoo_finance_downloader.py
pricedl/quotes/yfinance.py
pricedl/quotes/yfinance_downloader.py
as_price_download-0.4.0.dist-info/METADATA
as_price_download-0.4.0.dist-info/WHEEL
as_price_download-0.4.0.dist-info/entry_points.txt
as_price_download-0.4.0.dist-info/licenses/LICENSE
as_price_download-0.4.0.dist-info/RECORD
