Metadata-Version: 2.4
Name: as-price-download
Version: 0.4.0
Summary: Commodity price retrieval, storage, and export in format compatible with Plain-Text Accounting applications.
License-File: LICENSE
Requires-Python: >=3.12
Requires-Dist: asyncclick>=8.1.8
Requires-Dist: beanprice>=2.0.0
Requires-Dist: dotenv>=0.9.9
Requires-Dist: loguru>=0.7.3
Requires-Dist: pyeurofx>=0.6.4
Requires-Dist: requests>=2.32.3
Requires-Dist: yfinance>=0.2.59
